{"name":"test004","id":"com.bestbuy.testsuit.StoreCurdTestWithSteps:test004","testCaseName":"com.bestbuy.testsuit.StoreCurdTestWithSteps","testSteps":[{"number":1,"description":"Deleting store information with storeId: 25","duration":23,"startTime":"2023-01-03T14:10:48.034Z[Europe/London]","result":"SUCCESS","precondition":false,"children":[{"number":2,"description":"DELETE http://localhost:3030/stores/25\r\r","duration":0,"startTime":"2023-01-03T14:10:48.057Z[Europe/London]","result":"SUCCESS","restQuery":{"method":"DELETE","path":"http://localhost:3030/stores/25\r\r","content":"\r","contentType":"null","requestHeaders":"Accept\u003d*/*\r\r","requestCookies":"\r\r","responseHeaders":"X-Powered-By: Express\nAccess-Control-Allow-Origin: *\nAllow: GET,POST,PUT,PATCH,DELETE\nVary: Accept, Accept-Encoding\nContent-Type: application/json; charset\u003dutf-8\nContent-Length: 332\nETag: W/\"14c-GOmm444VPAs/Nm79T+6Dn1G+sCM\"\nDate: Tue, 03 Jan 2023 14:10:48 GMT\nConnection: keep-alive\r","responseCookies":"\r","responseBody":"{\n    \"id\": 25,\n    \"name\": \"Southridge\",\n    \"type\": \"BigBox\",\n    \"address\": \"4610 S 76th St\",\n    \"address2\": \"\",\n    \"city\": \"Greenfield\",\n    \"state\": \"WI\",\n    \"zip\": \"53220\",\n    \"lat\": 42.960411,\n    \"lng\": -88.006241,\n    \"hours\": \"Mon: 10-9; Tue: 10-9; Wed: 10-9; Thurs: 10-9; Fri: 10-9; Sat: 10-9; Sun: 10-8\",\n    \"createdAt\": \"2016-11-17T17:57:05.149Z\",\n    \"updatedAt\": \"2023-01-03T14:10:47.958Z\"\n}","statusCode":200},"precondition":false}]},{"number":3,"description":"Getting store information with studentId: 25","duration":23,"startTime":"2023-01-03T14:10:48.058Z[Europe/London]","result":"SUCCESS","precondition":false,"children":[{"number":4,"description":"GET http://localhost:3030/stores/25\r\r","duration":0,"startTime":"2023-01-03T14:10:48.081Z[Europe/London]","result":"SUCCESS","restQuery":{"method":"GET","path":"http://localhost:3030/stores/25\r\r","content":"\r","contentType":"null","requestHeaders":"Accept\u003d*/*\r\r","requestCookies":"\r\r","responseHeaders":"X-Powered-By: Express\nAccess-Control-Allow-Origin: *\nAllow: GET,POST,PUT,PATCH,DELETE\nContent-Type: application/json; charset\u003dutf-8\nContent-Length: 106\nETag: W/\"6a-s2rLko9/foW5NHi1k4n/yIxsS6k\"\nVary: Accept-Encoding\nDate: Tue, 03 Jan 2023 14:10:48 GMT\nConnection: keep-alive\r","responseCookies":"\r","responseBody":"{\n    \"name\": \"NotFound\",\n    \"message\": \"No record found for id \u002725\u0027\",\n    \"code\": 404,\n    \"className\": \"not-found\",\n    \"errors\": {\n        \n    }\n}","statusCode":404},"precondition":false}]}],"userStory":{"id":"com.bestbuy.testsuit.StoreCurdTestWithSteps","storyName":"Store curd test with steps","storyClassName":"com.bestbuy.testsuit.StoreCurdTestWithSteps","path":"com.bestbuy.testsuit","type":"story"},"featureTag":{"name":"Testsuit/Store curd test with steps","type":"story"},"title":"Delete the store and verify if the student is deleted!","tags":[{"name":"Testsuit/Store curd test with steps","type":"story"}],"startTime":"2023-01-03T14:10:48.034Z[Europe/London]","duration":48,"projectKey":"","manual":false,"testSource":"JUnit","result":"SUCCESS"}